pxtextmining/__init__.py
pxtextmining/factories/__init__.py
pxtextmining/factories/factory_data_load_and_split.py
pxtextmining/factories/factory_model_performance.py
pxtextmining/factories/factory_pipeline.py
pxtextmining/factories/factory_predict_unlabelled_text.py
pxtextmining/factories/factory_write_results.py
pxtextmining/helpers/__init__.py
pxtextmining/helpers/text_preprocessor.py
pxtextmining/params.py
pxtextmining/pipelines/__init__.py
pxtextmining/pipelines/multilabel_pipeline.py
pxtextmining/pipelines/sentiment_pipeline.py
pxtextmining-1.0.1.dist-info/LICENSE
pxtextmining-1.0.1.dist-info/METADATA
pxtextmining-1.0.1.dist-info/WHEEL
pxtextmining-1.0.1.dist-info/RECORD
