Metadata-Version: 2.1
Name: pxtextmining
Version: 1.0.1
Summary: Text classification of patient experience feedback.
Home-page: https://github.com/the-strategy-unit/pxtextmining
License: MIT
Author: CDU Data Science
Author-email: phudatascience@nottshc.nhs.uk
Requires-Python: >3.8,<3.11
Classifier: License :: OSI Approved :: MIT License
Classifier: Programming Language :: Python :: 3
Classifier: Programming Language :: Python :: 3.9
Classifier: Programming Language :: Python :: 3.10
Requires-Dist: joblib (>=1.2.0,<2.0.0)
Requires-Dist: matplotlib (>=3.3.2,<4.0.0)
Requires-Dist: numpy (>=1.22)
Requires-Dist: pandas (>=1.4.0,<2.0.0)
Requires-Dist: scikit-learn (==1.0.2)
Requires-Dist: scipy (>=1.10.1,<2.0.0)
Requires-Dist: tensorflow (==2.12.0)
Requires-Dist: transformers (>=4.26.1,<5.0.0)
Requires-Dist: xgboost (>=1.7.5,<2.0.0)
Project-URL: Documentation, https://the-strategy-unit.github.io/pxtextmining
Project-URL: Repository, https://github.com/the-strategy-unit/pxtextmining
